<?xml version="1.0" encoding="UTF-8"?><record_update table="sp_instance_carousel">
    <sp_instance_carousel action="DELETE">
        <active>true</active>
        <class_name/>
        <color>default</color>
        <css/>
        <glyph/>
        <id/>
        <interval>5000</interval>
        <order>1</order>
        <roles/>
        <short_description/>
        <size>md</size>
        <sp_column display_value="1">3328f4b197ba311070d034100153af41</sp_column>
        <sp_widget display_value="Carousel">cf1a5153cb21020000f8d856634c9c3c</sp_widget>
        <sys_class_name>sp_instance_carousel</sys_class_name>
        <sys_created_by>admin</sys_created_by>
        <sys_created_on>2023-11-30 23:52:01</sys_created_on>
        <sys_id>f571ffca973ab11070d034100153afb2</sys_id>
        <sys_mod_count>0</sys_mod_count>
        <sys_name/>
        <sys_package display_value="Gym Management" source="x_1117801_gym_mngt">5f9f328a976a311070d034100153af49</sys_package>
        <sys_policy/>
        <sys_scope display_value="Gym Management">5f9f328a976a311070d034100153af49</sys_scope>
        <sys_update_name>sp_instance_carousel_f571ffca973ab11070d034100153afb2</sys_update_name>
        <sys_updated_by>admin</sys_updated_by>
        <sys_updated_on>2023-11-30 23:52:01</sys_updated_on>
        <title/>
        <url/>
        <widget_parameters/>
    </sp_instance_carousel>
    <sys_translated_text action="DELETE" query="documentkey=f571ffca973ab11070d034100153afb2"/>
    <sys_update_version action="INSERT_OR_UPDATE">
        <action>DELETE</action>
        <application display_value="Gym Management">5f9f328a976a311070d034100153af49</application>
        <file_path/>
        <instance_id>ad1a86eddb54e9103050ac44d496196f</instance_id>
        <instance_name>dev147213</instance_name>
        <name>sp_instance_carousel_f571ffca973ab11070d034100153afb2</name>
        <payload><![CDATA[<?xml version="1.0" encoding="UTF-8"?><record_update table="sp_instance_carousel"><sp_instance_carousel action="INSERT_OR_UPDATE"><active>true</active><class_name/><color>default</color><css/><glyph/><id/><interval>5000</interval><order>1</order><roles/><short_description/><size>md</size><sp_column display_value="1">3328f4b197ba311070d034100153af41</sp_column><sp_widget display_value="Carousel">cf1a5153cb21020000f8d856634c9c3c</sp_widget><sys_class_name>sp_instance_carousel</sys_class_name><sys_created_by>admin</sys_created_by><sys_created_on>2023-11-30 23:52:01</sys_created_on><sys_id>f571ffca973ab11070d034100153afb2</sys_id><sys_mod_count>0</sys_mod_count><sys_name/><sys_package display_value="Gym Management" source="x_1117801_gym_mngt">5f9f328a976a311070d034100153af49</sys_package><sys_policy/><sys_scope display_value="Gym Management">5f9f328a976a311070d034100153af49</sys_scope><sys_update_name>sp_instance_carousel_f571ffca973ab11070d034100153afb2</sys_update_name><sys_updated_by>admin</sys_updated_by><sys_updated_on>2023-11-30 23:52:01</sys_updated_on><title/><url/><widget_parameters/></sp_instance_carousel><sys_translated_text action="delete_multiple" query="documentkey=f571ffca973ab11070d034100153afb2"/></record_update>]]></payload>
        <payload_hash>1758364144</payload_hash>
        <record_name/>
        <reverted_from/>
        <source>9348038697aa311070d034100153af46</source>
        <source_table>sys_update_set</source_table>
        <state>previous</state>
        <sys_created_by>admin</sys_created_by>
        <sys_created_on>2023-11-30 23:52:01</sys_created_on>
        <sys_id>3d71ffca973ab11070d034100153afb4</sys_id>
        <sys_mod_count>0</sys_mod_count>
        <sys_recorded_at>18c22a5843d0000001</sys_recorded_at>
        <sys_updated_by>admin</sys_updated_by>
        <sys_updated_on>2023-11-30 23:52:01</sys_updated_on>
        <type>Instance of Carousel</type>
        <update_guid>7171ffca993ab1102e37a5d7862111b4</update_guid>
        <update_guid_history>7171ffca993ab1102e37a5d7862111b4:1758364144</update_guid_history>
    </sys_update_version>
    <sys_metadata_delete action="INSERT_OR_UPDATE">
        <sys_audit_delete display_value="">5cd1bf0e973ab11070d034100153af56</sys_audit_delete>
        <sys_class_name>sys_metadata_delete</sys_class_name>
        <sys_created_by>admin</sys_created_by>
        <sys_created_on>2023-11-30 23:53:33</sys_created_on>
        <sys_db_object display_value="" name="sp_instance_carousel">sp_instance_carousel</sys_db_object>
        <sys_id>81123560cb7f4d87bf3d10ebefad7e89</sys_id>
        <sys_metadata>f571ffca973ab11070d034100153afb2</sys_metadata>
        <sys_mod_count>0</sys_mod_count>
        <sys_name/>
        <sys_package display_value="Gym Management" source="x_1117801_gym_mngt">5f9f328a976a311070d034100153af49</sys_package>
        <sys_parent/>
        <sys_policy/>
        <sys_scope display_value="Gym Management">5f9f328a976a311070d034100153af49</sys_scope>
        <sys_scope_delete display_value="">6ba2a1389bb44300b26741b3861b1000</sys_scope_delete>
        <sys_update_name>sp_instance_carousel_f571ffca973ab11070d034100153afb2</sys_update_name>
        <sys_update_version display_value="sp_instance_carousel_f571ffca973ab11070d034100153afb2">3d71ffca973ab11070d034100153afb4</sys_update_version>
        <sys_updated_by>admin</sys_updated_by>
        <sys_updated_on>2023-11-30 23:53:33</sys_updated_on>
    </sys_metadata_delete>
</record_update>
