<?xml version="1.0" encoding="UTF-8"?><record_update table="sp_instance">
    <sp_instance action="DELETE">
        <active>true</active>
        <class_name/>
        <color>primary</color>
        <css/>
        <glyph/>
        <id/>
        <order>2</order>
        <roles/>
        <short_description/>
        <size>md</size>
        <sp_column display_value="1">231c190697be711070d034100153afeb</sp_column>
        <sp_widget display_value="SC Catalog Item">3c29786e87133200e0ef0cf888cb0bdf</sp_widget>
        <sys_class_name>sp_instance</sys_class_name>
        <sys_created_by>admin</sys_created_by>
        <sys_created_on>2023-11-30 13:00:22</sys_created_on>
        <sys_id>805c514697be711070d034100153afc9</sys_id>
        <sys_mod_count>1</sys_mod_count>
        <sys_name/>
        <sys_package display_value="Gym Management" source="x_1117801_gym_mngt">5f9f328a976a311070d034100153af49</sys_package>
        <sys_policy/>
        <sys_scope display_value="Gym Management">5f9f328a976a311070d034100153af49</sys_scope>
        <sys_update_name>sp_instance_805c514697be711070d034100153afc9</sys_update_name>
        <sys_updated_by>admin</sys_updated_by>
        <sys_updated_on>2023-11-30 13:00:45</sys_updated_on>
        <title/>
        <url/>
        <widget_parameters><![CDATA[{
	"show_add_cart_button": {
		"value": "",
		"displayValue": ""
	},
	"show_field_validation_messages": {
		"value": "true",
		"displayValue": "true"
	},
	"show_add_to_wishlist_button": {
		"value": "true",
		"displayValue": "true"
	},
	"display_cart_on_right": {
		"value": "true",
		"displayValue": "true"
	},
	"show_less_description": {
		"value": "true",
		"displayValue": "true"
	},
	"hide_delivery_time": {
		"value": "false",
		"displayValue": "false"
	},
	"is_preview": {
		"value": "true",
		"displayValue": "true"
	}
}]]></widget_parameters>
    </sp_instance>
    <sys_translated_text action="DELETE" query="documentkey=805c514697be711070d034100153afc9"/>
    <sys_update_version action="INSERT_OR_UPDATE">
        <action>DELETE</action>
        <application display_value="Gym Management">5f9f328a976a311070d034100153af49</application>
        <file_path/>
        <instance_id>ad1a86eddb54e9103050ac44d496196f</instance_id>
        <instance_name>dev147213</instance_name>
        <name>sp_instance_805c514697be711070d034100153afc9</name>
        <payload>&lt;?xml version="1.0" encoding="UTF-8"?&gt;&lt;record_update table="sp_instance"&gt;&lt;sp_instance action="INSERT_OR_UPDATE"&gt;&lt;active&gt;true&lt;/active&gt;&lt;class_name/&gt;&lt;color&gt;primary&lt;/color&gt;&lt;css/&gt;&lt;glyph/&gt;&lt;id/&gt;&lt;order&gt;2&lt;/order&gt;&lt;roles/&gt;&lt;short_description/&gt;&lt;size&gt;md&lt;/size&gt;&lt;sp_column display_value="1"&gt;231c190697be711070d034100153afeb&lt;/sp_column&gt;&lt;sp_widget display_value="SC Catalog Item"&gt;3c29786e87133200e0ef0cf888cb0bdf&lt;/sp_widget&gt;&lt;sys_class_name&gt;sp_instance&lt;/sys_class_name&gt;&lt;sys_created_by&gt;admin&lt;/sys_created_by&gt;&lt;sys_created_on&gt;2023-11-30 13:00:22&lt;/sys_created_on&gt;&lt;sys_id&gt;805c514697be711070d034100153afc9&lt;/sys_id&gt;&lt;sys_mod_count&gt;1&lt;/sys_mod_count&gt;&lt;sys_name/&gt;&lt;sys_package display_value="Gym Management" source="x_1117801_gym_mngt"&gt;5f9f328a976a311070d034100153af49&lt;/sys_package&gt;&lt;sys_policy/&gt;&lt;sys_scope display_value="Gym Management"&gt;5f9f328a976a311070d034100153af49&lt;/sys_scope&gt;&lt;sys_update_name&gt;sp_instance_805c514697be711070d034100153afc9&lt;/sys_update_name&gt;&lt;sys_updated_by&gt;admin&lt;/sys_updated_by&gt;&lt;sys_updated_on&gt;2023-11-30 13:00:45&lt;/sys_updated_on&gt;&lt;title/&gt;&lt;url/&gt;&lt;widget_parameters&gt;&lt;![CDATA[{
	"show_add_cart_button": {
		"value": "",
		"displayValue": ""
	},
	"show_field_validation_messages": {
		"value": "true",
		"displayValue": "true"
	},
	"show_add_to_wishlist_button": {
		"value": "true",
		"displayValue": "true"
	},
	"display_cart_on_right": {
		"value": "true",
		"displayValue": "true"
	},
	"show_less_description": {
		"value": "true",
		"displayValue": "true"
	},
	"hide_delivery_time": {
		"value": "false",
		"displayValue": "false"
	},
	"is_preview": {
		"value": "true",
		"displayValue": "true"
	}
}]]&gt;&lt;/widget_parameters&gt;&lt;/sp_instance&gt;&lt;sys_translated_text action="delete_multiple" query="documentkey=805c514697be711070d034100153afc9"/&gt;&lt;/record_update&gt;</payload>
        <payload_hash>297615830</payload_hash>
        <record_name/>
        <reverted_from/>
        <source>9348038697aa311070d034100153af46</source>
        <source_table>sys_update_set</source_table>
        <state>previous</state>
        <sys_created_by>admin</sys_created_by>
        <sys_created_on>2023-11-30 13:00:45</sys_created_on>
        <sys_id>716c154697be711070d034100153af76</sys_id>
        <sys_mod_count>0</sys_mod_count>
        <sys_recorded_at>18c2051426a0000001</sys_recorded_at>
        <sys_updated_by>admin</sys_updated_by>
        <sys_updated_on>2023-11-30 13:00:45</sys_updated_on>
        <type>Instance</type>
        <update_guid>396c154658be71104ed201103d4b5375</update_guid>
        <update_guid_history>396c154658be71104ed201103d4b5375:297615830,885c514653be7110439a582b478c83ca:267317300</update_guid_history>
    </sys_update_version>
    <sys_metadata_delete action="INSERT_OR_UPDATE">
        <sys_audit_delete display_value="">a88c554697be711070d034100153af83</sys_audit_delete>
        <sys_class_name>sys_metadata_delete</sys_class_name>
        <sys_created_by>admin</sys_created_by>
        <sys_created_on>2023-11-30 13:01:13</sys_created_on>
        <sys_db_object display_value="" name="sp_instance">sp_instance</sys_db_object>
        <sys_id>0641d522fb5449bf803642e7891d1281</sys_id>
        <sys_metadata>805c514697be711070d034100153afc9</sys_metadata>
        <sys_mod_count>0</sys_mod_count>
        <sys_name/>
        <sys_package display_value="Gym Management" source="x_1117801_gym_mngt">5f9f328a976a311070d034100153af49</sys_package>
        <sys_parent/>
        <sys_policy/>
        <sys_scope display_value="Gym Management">5f9f328a976a311070d034100153af49</sys_scope>
        <sys_scope_delete display_value="">6ba2a1389bb44300b26741b3861b1000</sys_scope_delete>
        <sys_update_name>sp_instance_805c514697be711070d034100153afc9</sys_update_name>
        <sys_update_version display_value="sp_instance_805c514697be711070d034100153afc9">716c154697be711070d034100153af76</sys_update_version>
        <sys_updated_by>admin</sys_updated_by>
        <sys_updated_on>2023-11-30 13:01:13</sys_updated_on>
    </sys_metadata_delete>
</record_update>
